{
    "version": "",
    "username": "Filipe Leuch Bonfim",
    "github_username": "filipe1309",
    "project_name": "NodeJS: Advanced Concepts",
    "project_repo_name": "ud-nodejs-advanced-concepts",
    "project_repo_link": "https://github.com/filipe1309/ud-nodejs-advanced-concepts.git",
    "course_source": "Udemy",
    "course_name": "NodeJS: Advanced Concepts",
    "course_link": "https://www.udemy.com/course/advanced-node-for-developers",
    "course_type": "class",
    "course_multiple": "false",
    "vcs": "false"
}
